readme_llm7_gen/__init__.py
readme_llm7_gen-2025.9.71453.dist-info/licenses/LICENSE
readme_llm7_gen-2025.9.71453.dist-info/METADATA
readme_llm7_gen-2025.9.71453.dist-info/WHEEL
readme_llm7_gen-2025.9.71453.dist-info/top_level.txt
readme_llm7_gen-2025.9.71453.dist-info/RECORD
