Metadata-Version: 2.4
Name: readme_llm7_gen
Version: 2025.9.71453
Summary: A package for generating README.md files using LLMs
Home-page: https://github.com/chigwell/readme_llm7_gen
Author: Eugene Evstafev
Author-email: hi@eugene.plus
Classifier: Programming Language :: Python :: 3
Classifier: License :: OSI Approved :: MIT License
Classifier: Operating System :: OS Independent
Requires-Python: >=3.6
License-File: LICENSE
Dynamic: author
Dynamic: author-email
Dynamic: classifier
Dynamic: description
Dynamic: description-content-type
Dynamic: home-page
Dynamic: license-file
Dynamic: requires-python
Dynamic: summary
